<?xml version="1.0" encoding="utf-8" ?>
<dwsync>
<file name="popper.min.js" server="files.000webhost.com/public_html/" local="132152632580000000" remote="132309887400000000" Dst="2" />
<file name="jquery-3.3.1.min.js" server="files.000webhost.com/public_html/" local="132152632580000000" remote="132310161000000000" Dst="2" />
<file name="bootstrap-4.3.1.js" server="files.000webhost.com/public_html/" local="132152632580000000" remote="132309887400000000" Dst="2" />
<file name="jquery-3.5.0.min.js" server="files.000webhost.com/public_html/" local="132324167491260593" remote="132324797400000000" Dst="2" />
<file name="jquery.nanogallery2.min.js" server="files.000webhost.com/public_html/" local="132325774382430942" remote="132332749200000000" Dst="2" />
<file name="jquery.scrollme.js" server="files.000webhost.com/public_html/" local="132331014001912008" remote="132332749200000000" Dst="2" />
<file name="nanogallery2.min.css" server="files.000webhost.com/public_html/" local="132326638006430280" remote="132332749200000000" Dst="2" />
<file name="jquery.scrollme.min.js" server="files.000webhost.com/public_html/" local="132332831932744288" remote="132341353200000000" Dst="2" />
<file name="fontawesome.min.js" server="files.000webhost.com/public_html/" local="132332841899187722" remote="132341353200000000" Dst="2" />
<file name="brands.min.js" server="files.000webhost.com/public_html/" local="132332841488740663" remote="132341353200000000" Dst="2" />
<file name="solid.min.js" server="files.000webhost.com/public_html/" local="132332841542065617" remote="132341353200000000" Dst="2" />
<file name="scroll.js" server="files.000webhost.com/public_html/" local="132335934676761341" remote="132336017400000000" Dst="2" />
<file name="lazysizes.min.js" server="files.000webhost.com/public_html/" local="132337138704225981" remote="132341353200000000" Dst="2" />
<file name="smooth_ scroll.js" server="files.000webhost.com/public_html/" local="132337792866691011" remote="132341353200000000" Dst="2" />
<file name="smooth-scroll.polyfills.min.js" server="files.000webhost.com/public_html/" local="132337935479715003" remote="132341353200000000" Dst="2" />
<file name="loadCSS.js" server="files.000webhost.com/public_html/" local="132338867026714516" remote="132338797200000000" Dst="2" />
<file name="bouncer.polyfills.min.js" server="files.000webhost.com/public_html/" local="132340439565115383" remote="132341353200000000" Dst="2" />
<file name="api.min.js" server="files.000webhost.com/public_html/" local="132340480223384533" remote="132340428600000000" Dst="2" />
</dwsync>